jour_ouvre.py
jour_ouvre-0.1.dist-info/METADATA
jour_ouvre-0.1.dist-info/WHEEL
jour_ouvre-0.1.dist-info/entry_points.txt
jour_ouvre-0.1.dist-info/top_level.txt
jour_ouvre-0.1.dist-info/RECORD
