Metadata-Version: 2.1
Name: jour-ouvre
Version: 0.1
Summary: Détecteur de jours ouvrés.
Home-page: UNKNOWN
Author: Johanne PEREAU
Author-email: johanne.pereau@gmail.com
License: MIT License
Platform: UNKNOWN
Classifier: Development Status :: 1 - Planning
Classifier: Intended Audience :: Information Technology
Classifier: License :: OSI Approved :: MIT License
Classifier: Natural Language :: French
Classifier: Programming Language :: Python :: 3
Requires-Python: >=3.6
